revup/__init__.py
revup/__main__.py
revup/amend.py
revup/cherry_pick.py
revup/config.py
revup/git.py
revup/github.py
revup/github_real.py
revup/github_utils.py
revup/logs.py
revup/restack.py
revup/revup.py
revup/shell.py
revup/toolkit.py
revup/topic_stack.py
revup/types.py
revup/upload.py
revup/man1/__init__.py
revup/man1/amend.1.gz
revup/man1/cherry-pick.1.gz
revup/man1/restack.1.gz
revup/man1/revup.1.gz
revup/man1/upload.1.gz
revup-0.0.1.dist-info/LICENSE
revup-0.0.1.dist-info/METADATA
revup-0.0.1.dist-info/WHEEL
revup-0.0.1.dist-info/entry_points.txt
revup-0.0.1.dist-info/top_level.txt
revup-0.0.1.dist-info/RECORD
