Metadata-Version: 2.1
Name: revup
Version: 0.0.1
Summary: Code review and workflow toolkit for git / github
Home-page: https://github.com/skydio/revup
Author: Jerry Zhang
Author-email: jerry@skydio.com
Project-URL: Bug Tracker, https://github.com/skydio/revup/issues
Classifier: Programming Language :: Python :: 3
Classifier: License :: OSI Approved :: MIT License
Classifier: Operating System :: OS Independent
Requires-Python: >=3.8
License-File: LICENSE
Requires-Dist: aiohttp
Requires-Dist: asyncio
Requires-Dist: configparser
Requires-Dist: dataclasses
Requires-Dist: rich
